fintest/__init__.py
fintest-0.1.0.dist-info/LICENSE
fintest-0.1.0.dist-info/METADATA
fintest-0.1.0.dist-info/WHEEL
fintest-0.1.0.dist-info/top_level.txt
fintest-0.1.0.dist-info/RECORD
