Metadata-Version: 2.1
Name: fintest
Version: 0.1.0
Summary: Functional and Integration Testing toolkit for python.
Home-page: https://github.com/kashifpk/fintest
Author: Kashif Iftikhar
License: MIT
Platform: UNKNOWN
Classifier: Programming Language :: Python :: 3
Requires-Python: >=3.8
License-File: LICENSE
